pytuft/__init__.py
pytuft/pytuft.py
pytuft/pytuft_config.py
pyTuft-1.0.0.dist-info/LICENSE
pyTuft-1.0.0.dist-info/METADATA
pyTuft-1.0.0.dist-info/WHEEL
pyTuft-1.0.0.dist-info/top_level.txt
pyTuft-1.0.0.dist-info/RECORD
