Metadata-Version: 2.1
Name: pyTuft
Version: 1.0.0
Summary: A Truffle-like tool for Python smart contracts
Home-page: https://github.com/OmneDAO/pyTuft
Author: Your Name
Author-email: your.email@example.com
License: UNKNOWN
Platform: UNKNOWN
Classifier: Programming Language :: Python :: 3
Classifier: License :: OSI Approved :: MIT License
Classifier: Operating System :: OS Independent
Requires-Python: >=3.6
License-File: LICENSE
Requires-Dist: requests
Requires-Dist: argparse
